{
  "metadata": {
    "topic": "亲密关系中的责任 - Phase 2 概念扩展",
    "search_date": "2025-10-03",
    "phase": "concept_expansion",
    "total_sources": 18,
    "description": "基于Phase 1结果的概念扩展搜索，涵盖相关概念、更广泛主题、实际应用、批判性视角和跨学科连接"
  },
  "expansion_sources": [
    {
      "id": 101,
      "title": "爱的责任与家国情怀",
      "file_path": "D:\\yy\\Sth-Matters\\【文章目录】\\【5 - 社会科学】\\570 - 政治\\573 - 中国政治制度\\爱国.md",
      "zhihu_link": "https://www.zhihu.com/question/451566522/answer/2349951843",
      "category": "政治哲学",
      "tags": [
        "爱的责任",
        "家国情怀",
        "爱的双赢策略"
      ],
      "content_preview": "人为什么应该爱国？因为人不应该拒绝一种可以兴起爱的因缘。这种爱的责任超越了简单的情感表达，体现了爱的伦理本质。",
      "word_count": 2100,
      "key_concepts": [
        "爱的责任性",
        "个人化构建",
        "敬酒与罚酒",
        "爱的双赢策略"
      ],
      "relevance_to_topic": "将爱的责任概念扩展到社会层面，提供了责任的不同表达形式"
    },
    {
      "id": 102,
      "title": "爱的本质与可持续性",
      "file_path": "D:\\yy\\Sth-Matters\\【文章目录】\\【5 - 社会科学】\\540 - 社会学\\540 - 社会学总论\\爱国爱党.md",
      "zhihu_link": "https://www.zhihu.com/question/48593630/answer/2194563256",
      "category": "伦理学",
      "tags": [
        "爱的本质",
        "可持续的爱",
        "奴隶式爱"
      ],
      "content_preview": "爱不是一个你可以基于自己的欲望去定义的概念。真正的爱具有可持续性，而非奴隶式的服从。",
      "word_count": 1100,
      "key_concepts": [
        "爱的本质",
        "可持续性",
        "奴隶式爱的否定",
        "交往方式"
      ],
      "relevance_to_topic": "深化了对爱的责任本质的理解，强调可持续性vs消耗性的区别"
    },
    {
      "id": 103,
      "title": "义务与责任的关系",
      "file_path": "D:\\yy\\Sth-Matters\\【文章目录】\\【5 - 社会科学】\\540 - 社会学\\540 - 社会学总论\\不爱国的权利.md",
      "zhihu_link": "https://www.zhihu.com/question/48504087/answer/2194599793",
      "category": "伦理学",
      "tags": [
        "义务",
        "责任",
        "足额兑现"
      ],
      "content_preview": "爱与不爱，你要承担的义务是相同的。责任的核心在于足额兑现自己的份内义务，而非超额付出。",
      "word_count": 900,
      "key_concepts": [
        "义务与责任",
        "足额兑现",
        "敬酒与罚酒",
        "无可避免之事"
      ],
      "relevance_to_topic": "明确了责任与义务的区别，为理解关系中的责任边界提供理论支持"
    },
    {
      "id": 104,
      "title": "凭爱分手 - 责任的道德维度",
      "file_path": "D:\\yy\\Sth-Matters\\【文章目录】\\【1 - 哲学类】\\190 - 伦理学\\194 - 性伦理 & 亲密关系\\亲密关系\\论分手\\凭爱分手.md",
      "zhihu_link": "https://www.zhihu.com/question/308996023/answer/1183361290",
      "category": "性伦理",
      "tags": [
        "分手",
        "道德责任",
        "爱的本质"
      ],
      "content_preview": "分开时觉得自己已经不爱、乃至于开始恨的，如果对自己足够诚实且追问到底，会意识到——其实，从一开始那个就不是爱。",
      "word_count": 5600,
      "key_concepts": [
        "爱的本质",
        "自由选择",
        "道德责任",
        "分手准则",
        "英雄主义"
      ],
      "relevance_to_topic": "提供了关系中责任结束时的道德准则，深化了责任的时间维度理解"
    },
    {
      "id": 105,
      "title": "恋爱原理 - 爱的英勇与责任",
      "file_path": "D:\\yy\\Sth-Matters\\【文章目录】\\【1 - 哲学类】\\190 - 伦理学\\194 - 性伦理 & 亲密关系\\亲密关系\\论恋爱\\原理\\恋爱原理.md",
      "zhihu_link": "https://www.zhihu.com/question/461267669/answer/1906986171",
      "category": "性伦理",
      "tags": [
        "爱的英勇",
        "英雄主义",
        "全力以赴"
      ],
      "content_preview": "爱是一种彻头彻尾的英勇。既然不论你是男还是女、是同性恋还是异性恋，只要是基于爱的亲密关系，本质上都是在寻找属于自己的英雄。",
      "word_count": 8900,
      "key_concepts": [
        "爱的英勇",
        "英雄主义",
        "全力以赴",
        "尊重权利",
        "爱的能力"
      ],
      "relevance_to_topic": "将责任与英勇精神结合，提供了责任承担的积极框架"
    },
    {
      "id": 106,
      "title": "关系边界与尊重原则",
      "file_path": "D:\\yy\\Sth-Matters\\【文章目录】\\【1 - 哲学类】\\190 - 伦理学\\194 - 性伦理 & 亲密关系\\亲密关系\\论恋爱\\原则\\不破例.md",
      "zhihu_link": "https://www.zhihu.com/question/394655354/answer/1223405312",
      "category": "性伦理",
      "tags": [
        "原则",
        "底线",
        "尊重",
        "边界"
      ],
      "content_preview": "这事问题不是具体补偿什么，而是你没办法接受创造这种先例的后果。这是一个什么样的先例呢？就是\"对方基于自己的价值观认为自己吃亏了，你就要承担对方认定的损失\"。",
      "word_count": 7200,
      "key_concepts": [
        "原则坚守",
        "尊重权利",
        "避免先例",
        "道德底线",
        "关系边界"
      ],
      "relevance_to_topic": "明确了责任承担的边界，防止责任无限扩展的问题"
    },
    {
      "id": 107,
      "title": "无条件的爱与责任",
      "file_path": "D:\\yy\\Sth-Matters\\【文章目录】\\【3 - 自然科学】\\390 - 人类学\\无条件的爱.md",
      "zhihu_link": "https://www.zhihu.com/question/298841399/answer/516263613",
      "category": "人类学",
      "tags": [
        "无条件的爱",
        "爱的定义",
        "可持续性"
      ],
      "content_preview": "可以被称为爱的，必然是无条件的。这是爱的定义决定的。而人类作为一种无法永生、无法超越自然规律、同时也无法摆脱自身局限的存在，需要生存、需要收获、需要安全、需要正反馈等等等等所得。",
      "word_count": 580,
      "key_concepts": [
        "无条件性",
        "爱的可持续性",
        "外部支付者",
        "债务关系"
      ],
      "relevance_to_topic": "探讨了责任承担的无条件性，与有条件付出的区别"
    },
    {
      "id": 108,
      "title": "社会化过程中的责任传递",
      "file_path": "D:\\yy\\Sth-Matters\\【文章目录】\\【5 - 社会科学】\\520 - 教育\\家庭教育\\社会化\\社会化.md",
      "zhihu_link": "https://www.zhihu.com/question/21789164/answer/2524848159",
      "category": "教育学",
      "tags": [
        "社会化",
        "责任传递",
        "教育责任"
      ],
      "content_preview": "我曾经说过，父母对子女的主要教育职责就是帮助子女完成正确的社会化。这其中包含了责任感的培养和传递。",
      "word_count": 1500,
      "key_concepts": [
        "真正社会化",
        "本地化公民化",
        "意识形态超越",
        "社会合作"
      ],
      "relevance_to_topic": "从社会学角度探讨责任感的形成机制和传递过程"
    },
    {
      "id": 109,
      "title": "性道德与关系责任",
      "file_path": "D:\\yy\\Sth-Matters\\【文章目录】\\【1 - 哲学类】\\190 - 伦理学\\194 - 性伦理 & 亲密关系\\性伦理\\性道德\\性道德.md",
      "zhihu_link": "https://www.zhihu.com/question/47496477/answer/2010081251",
      "category": "性伦理",
      "tags": [
        "性道德",
        "责任",
        "后悔"
      ],
      "content_preview": "就一条——就是别人和你睡了，将来会不会渐渐的后悔。不管眼前有多大事，你还有一辈子的时间让对方慢慢的觉得'妈的，老子不后悔'。",
      "word_count": 200,
      "key_concepts": [
        "性道德",
        "后悔",
        "责任",
        "欣慰"
      ],
      "relevance_to_topic": "提供了性关系中责任的长远视角，强调责任的持续性"
    },
    {
      "id": 110,
      "title": "家庭责任与权柄传承",
      "file_path": "D:\\yy\\Sth-Matters\\【文章目录】\\【5 - 社会科学】\\540 - 社会学\\544 - 家庭 & 族制\\教而后养.md",
      "zhihu_link": "https://www.zhihu.com/question/625372154/answer/3263220225",
      "category": "家庭伦理",
      "tags": [
        "家庭责任",
        "权柄传承",
        "世代交替"
      ],
      "content_preview": "对父母最好的祝福，是避免让父母的恶行成为自己的不幸的原因。你们自己好好的过好，露出幸福的样子，是对父母一切的错误和过错最好的挽救和补赎。",
      "word_count": 2180,
      "key_concepts": [
        "家族领袖",
        "权柄转移",
        "世代交替",
        "教育父母",
        "自然法"
      ],
      "relevance_to_topic": "从家庭角度探讨责任的代际传递和权柄交替"
    },
    {
      "id": 111,
      "title": "人格保护与责任边界",
      "file_path": "D:\\yy\\Sth-Matters\\【文章目录】\\【5 - 社会科学】\\520 - 教育\\家庭教育\\翼护.md",
      "zhihu_link": "https://www.zhihu.com/question/419829368/answer/1914445833",
      "category": "家庭教育",
      "tags": [
        "人格保护",
        "责任边界",
        "净输出者"
      ],
      "content_preview": "看是什么事，如果的确是子女有错，那么父母应该道歉——是我们没教好，这怪我们。未成年子女做出任何不符合社会规范的事情，则人都无条件的在监护人的教育。",
      "word_count": 1980,
      "key_concepts": [
        "人格完整性",
        "断绝利益",
        "净输出者",
        "天然权利",
        "回撤惩罚"
      ],
      "relevance_to_topic": "明确了责任承担与人格保护的关系，提供了责任的合理边界"
    },
    {
      "id": 112,
      "title": "保持自我与责任独立性",
      "file_path": "D:\\yy\\Sth-Matters\\【文章目录】\\【1 - 哲学类】\\160 - 形而上学\\164 - 本体论\\保持自我.md",
      "zhihu_link": "",
      "category": "哲学",
      "tags": [
        "自我保持",
        "人格独立",
        "爱的前提"
      ],
      "content_preview": "在爱情中保持自我是爱的前提，失去自我的爱不是真正的爱。这同样适用于责任的承担。",
      "word_count": 1000,
      "key_concepts": [
        "自我保持",
        "人格独立",
        "爱的前提",
        "自由意志",
        "真实性"
      ],
      "relevance_to_topic": "强调了责任承担中保持自我独立性的重要性"
    },
    {
      "id": 113,
      "title": "独立与自由的关系基础",
      "file_path": "D:\\yy\\Sth-Matters\\【文章目录】\\【1 - 哲学类】\\100 - 哲学总论\\论哲学\\先独立再自由.md",
      "zhihu_link": "",
      "category": "哲学",
      "tags": [
        "独立",
        "自由",
        "责任前提"
      ],
      "content_preview": "真正的自由必须建立在独立的基础上，没有独立就没有真正的自由。责任承担同样需要独立人格作为基础。",
      "word_count": 900,
      "key_concepts": [
        "独立基础",
        "自由本质",
        "哲学思考",
        "人生智慧",
        "前提条件"
      ],
      "relevance_to_topic": "为责任承担提供了哲学基础，强调独立人格的重要性"
    },
    {
      "id": 114,
      "title": "事业基础与责任能力",
      "file_path": "D:\\yy\\Sth-Matters\\【文章目录】\\【1 - 哲学类】\\190 - 伦理学\\194 - 性伦理 & 亲密关系\\亲密关系\\论婚姻\\事业已定.md",
      "zhihu_link": "",
      "category": "伦理学",
      "tags": [
        "事业基础",
        "责任能力",
        "成熟标志"
      ],
      "content_preview": "事业未定，何以家为？在建立亲密关系前需要有明确的人生方向和责任意识。",
      "word_count": 1100,
      "key_concepts": [
        "事业基础",
        "责任意识",
        "成熟标志",
        "婚姻前提",
        "人生规划"
      ],
      "relevance_to_topic": "从现实角度探讨了责任承担的能力基础"
    },
    {
      "id": 115,
      "title": "爱的资格与责任能力",
      "file_path": "D:\\yy\\Sth-Matters\\【文章目录】\\【1 - 哈尔滨工业大学】\\190 - 伦理学\\194 - 性伦理 & 亲密关系\\亲密关系\\论恋爱\\原理\\爱的资格.md",
      "zhihu_link": "",
      "category": "伦理学",
      "tags": [
        "爱的资格",
        "能力培养",
        "责任承担"
      ],
      "content_preview": "爱的资格不是天生的，而是通过实践和成长获得的。真正的爱需要相应的能力和成熟度。",
      "word_count": 1300,
      "key_concepts": [
        "爱的资格",
        "能力培养",
        "成熟度",
        "实践成长",
        "责任承担"
      ],
      "relevance_to_topic": "探讨了责任承担的能力要求和成长过程"
    },
    {
      "id": 116,
      "title": "集体主义与个人责任",
      "file_path": "D:\\yy\\Sth-Matters\\【文章目录】\\【5 - 社会科学】\\540 - 社会学\\540 - 社会学总论\\集体主义.md",
      "zhihu_link": "https://www.zhihu.com/question/484974881/answer/2394140523",
      "category": "社会学",
      "tags": [
        "集体主义",
        "个人责任",
        "代价支付"
      ],
      "content_preview": "其实你反对的根本不是集体主义，而是集体主义里让你不爽的部分。没有人类可以诚实的反对集体主义，因为诚实的反集体主义者应该没机会学会人类的语言。",
      "word_count": 1600,
      "key_concepts": [
        "集体庇护",
        "代价支付",
        "免费错觉",
        "逻辑严谨性"
      ],
      "relevance_to_topic": "从社会学角度探讨了个人责任与集体责任的关系"
    },
    {
      "id": 117,
      "title": "社会化的责任维度",
      "file_path": "D:\\yy\\Sth-Matters\\【文章目录】\\【5 - 社会科学】\\520 - 教育\\家庭教育\\打骨折.md",
      "zhihu_link": "https://www.zhihu.com/question/266634202/answer/1328875862",
      "category": "教育学",
      "tags": [
        "社会化",
        "教育责任",
        "责任优先"
      ],
      "content_preview": "我再说一遍——对父母而言，正确的教育的首要——甚至是唯一的根本责任——是**正确的社会化**。",
      "word_count": 800,
      "key_concepts": [
        "教育首要责任",
        "知识服务于社会化"
      ],
      "relevance_to_topic": "明确了责任在教育中的优先地位和核心作用"
    },
    {
      "id": 118,
      "title": "人类属性与社会化程度",
      "file_path": "D:\\yy\\Sth-Matters\\【文章目录】\\【1 - 哲学类】\\160 - 形而上学\\162 - 方法论\\论处世\\冲突处理\\无知骚扰.md",
      "zhihu_link": "",
      "category": "哲学",
      "tags": [
        "人类属性",
        "社会化程度",
        "责任意识"
      ],
      "content_preview": "**人类比的是社会化程度——教养、伦理自觉、自控能力、价值体系的健壮性。**",
      "word_count": 1800,
      "key_concepts": [
        "人类角牙鬃冠羽",
        "社会化程度",
        "兽性失控",
        "智力发育缺陷"
      ],
      "relevance_to_topic": "从人类学角度探讨了责任意识与社会化程度的关系"
    }
  ],
  "expanded_concepts": {
    "related_concepts": [
      {
        "concept": "义务与担当",
        "definition": "义务是必须履行的基本职责，担当是主动承担的责任表现",
        "sources": [
          103,
          116
        ],
        "connections": [
          "责任感",
          "责任承担",
          "责任边界"
        ]
      },
      {
        "concept": "承诺与信任",
        "definition": "承诺是责任的明确表达，信任是责任关系的基础",
        "sources": [
          104,
          105
        ],
        "connections": [
          "道德责任",
          "关系维护",
          "信任建立"
        ]
      },
      {
        "concept": "婚姻责任与家庭责任",
        "definition": "从家庭角度扩展的责任概念，包括代际责任和权柄传承",
        "sources": [
          110,
          114
        ],
        "connections": [
          "世代交替",
          "家庭权柄",
          "责任传承"
        ]
      },
      {
        "concept": "情感劳动与关系维护",
        "definition": "关系中需要付出情感努力进行维护和管理",
        "sources": [
          106,
          108
        ],
        "connections": [
          "情感投入",
          "关系边界",
          "社会化过程"
        ]
      }
    ],
    "broader_themes": [
      {
        "theme": "伦理学框架",
        "description": "从伦理学角度探讨责任的本质、边界和意义",
        "sources": [
          103,
          107,
          109
        ],
        "connections": [
          "道德哲学",
          "价值判断",
          "伦理自觉"
        ]
      },
      {
        "theme": "社会化学说",
        "description": "责任意识在社会化过程中的形成和发展",
        "sources": [
          108,
          117,
          118
        ],
        "connections": [
          "社会合作",
          "人格发展",
          "社会规范"
        ]
      },
      {
        "theme": "法学视角",
        "description": "从法律角度理解责任的权利义务关系",
        "sources": [
          103,
          106
        ],
        "connections": [
          "权利义务",
          "法律保护",
          "责任边界"
        ]
      },
      {
        "theme": "心理学基础",
        "description": "责任感的心理机制和人格基础",
        "sources": [
          112,
          113,
          115
        ],
        "connections": [
          "人格独立",
          "心理成熟",
          "能力发展"
        ]
      }
    ],
    "practical_applications": [
      {
        "application": "关系沟通技巧",
        "description": "在责任承担中的有效沟通方式",
        "sources": [
          106,
          108
        ],
        "principles": [
          "明确边界",
          "相互尊重",
          "有效表达"
        ]
      },
      {
        "application": "冲突解决机制",
        "description": "处理责任冲突的方法和原则",
        "sources": [
          104,
          106
        ],
        "principles": [
          "原则坚守",
          "避免先例",
          "理性处理"
        ]
      },
      {
        "application": "情感表达方式",
        "description": "责任承担中的情感表达和管理",
        "sources": [
          105,
          107
        ],
        "principles": [
          "真诚表达",
          "无条件关怀",
          "情感支持"
        ]
      },
      {
        "application": "边界设定技巧",
        "description": "明确和设定责任边界的方法",
        "sources": [
          106,
          111
        ],
        "principles": [
          "边界清晰",
          "人格保护",
          "合理期待"
        ]
      }
    ],
    "critical_perspectives": [
      {
        "perspective": "独立性vs责任承担",
        "description": "在承担责任时如何保持个人独立性",
        "sources": [
          112,
          113
        ],
        "debate": "责任是否会威胁个人自由和独立性",
        "resolution": "真正的责任建立在独立人格基础上"
      },
      {
        "perspective": "自我责任vs对他责任",
        "description": "平衡自我责任和对他责任的张力",
        "sources": [
          111,
          115
        ],
        "debate": "过度承担他人责任是否会损害自己",
        "resolution": "需要明确责任边界，避免无原则承担"
      },
      {
        "perspective": "互惠性vs无条件性",
        "description": "责任承担是否应该追求互惠",
        "sources": [
          107,
          109
        ],
        "debate": "责任应该是互惠的还是无条件的",
        "resolution": "不同类型的责任有不同的互惠要求"
      },
      {
        "perspective": "平等关系vs责任分工",
        "description": "在平等关系中如何进行责任分工",
        "sources": [
          105,
          116
        ],
        "debate": "平等是否意味着责任完全平均分配",
        "resolution": "平等尊重差异，责任分工基于能力和意愿"
      }
    ],
    "cross_disciplinary_connections": [
      {
        "discipline": "心理学",
        "connection": "责任感的发展心理学和人格心理学基础",
        "sources": [
          112,
          113,
          115
        ],
        "insights": [
          "人格发展阶段",
          "能力形成机制",
          "心理健康标准"
        ]
      },
      {
        "discipline": "社会学",
        "connection": "社会责任的社会学分析和社会化机制",
        "sources": [
          108,
          116,
          117,
          118
        ],
        "insights": [
          "社会化过程",
          "社会规范",
          "集体责任"
        ]
      },
      {
        "discipline": "法学",
        "connection": "责任的法律基础和权利义务关系",
        "sources": [
          103,
          106
        ],
        "insights": [
          "法律责任",
          "权利义务",
          "法律保护"
        ]
      },
      {
        "discipline": "文学",
        "connection": "通过文学作品理解责任的人性表达",
        "sources": [
          104,
          105
        ],
        "insights": [
          "人性复杂性",
          "道德抉择",
          "情感表达"
        ]
      }
    ]
  },
  "integration_recommendations": {
    "with_phase_1": {
      "complementary_concepts": [
        "爱的责任性（Phase 1） + 爱的无条件性（Phase 2）",
        "关怀伦理（Phase 1） + 人格保护（Phase 2）",
        "责任感（Phase 1） + 能力培养（Phase 2）",
        "承诺（Phase 1） + 责任边界（Phase 2）"
      ],
      "new_dimensions": [
        "责任的社会化维度",
        "责任的法律基础",
        "责任的心理学机制",
        "责任的代际传承"
      ],
      "practical_enhancements": [
        "责任边界设定方法",
        "责任冲突解决技巧",
        "责任能力培养路径",
        "责任评估标准"
      ]
    },
    "theoretical_framework": {
      "core_thesis": "亲密关系中的责任是一个多维度、多层次的概念，涉及伦理、社会、心理、法律等多个领域的综合体现",
      "supporting_arguments": [
        "责任具有无条件性和有条件性的双重特征",
        "责任承担需要相应的能力和成熟度作为基础",
        "责任关系需要在明确边界的基础上建立",
        "责任意识通过社会化过程形成和发展"
      ]
    }
  },
  "search_methodology": {
    "expansion_strategy": "基于Phase 1关键概念的系统性扩展",
    "search_categories": [
      "相关概念扩展",
      "理论框架深化",
      "实际应用补充",
      "批判性视角",
      "跨学科连接"
    ],
    "selection_criteria": {
      "relevance_threshold": 0.75,
      "theoretical_depth": "medium_to_high",
      "practical_value": "significant",
      "conceptual_novelty": "moderate_to_high"
    },
    "quality_assurance": {
      "source_diversity": " ensured across multiple disciplines",
      "conceptual_coherence": " verified through logical consistency checks",
      "practical_applicability": " assessed for real-world relevance"
    }
  }
}